CHANGES.txt
CONTRIBUTORS.txt
MANIFEST.in
README.txt
setup.cfg
setup.py
docs/LICENSE.GPL
docs/LICENSE.txt
src/zettwerk/__init__.py
src/zettwerk.mobiletheming.egg-info/PKG-INFO
src/zettwerk.mobiletheming.egg-info/SOURCES.txt
src/zettwerk.mobiletheming.egg-info/dependency_links.txt
src/zettwerk.mobiletheming.egg-info/entry_points.txt
src/zettwerk.mobiletheming.egg-info/namespace_packages.txt
src/zettwerk.mobiletheming.egg-info/not-zip-safe
src/zettwerk.mobiletheming.egg-info/requires.txt
src/zettwerk.mobiletheming.egg-info/top_level.txt
src/zettwerk/mobiletheming/__init__.py
src/zettwerk/mobiletheming/configure.zcml
src/zettwerk/mobiletheming/genericsetup.py
src/zettwerk/mobiletheming/interfaces.py
src/zettwerk/mobiletheming/profiles.zcml
src/zettwerk/mobiletheming/testing.py
src/zettwerk/mobiletheming/transform.py
src/zettwerk/mobiletheming/vocabularies.py
src/zettwerk/mobiletheming/Extensions/Install.py
src/zettwerk/mobiletheming/browser/__init__.py
src/zettwerk/mobiletheming/browser/configure.zcml
src/zettwerk/mobiletheming/browser/controlpanel.py
src/zettwerk/mobiletheming/browser/view.py
src/zettwerk/mobiletheming/browser/images/z.png
src/zettwerk/mobiletheming/browser/scripts/me.redirect.min.js
src/zettwerk/mobiletheming/profiles/default/componentregistry.xml
src/zettwerk/mobiletheming/profiles/default/controlpanel.xml
src/zettwerk/mobiletheming/profiles/default/cssregistry.xml
src/zettwerk/mobiletheming/profiles/default/jsregistry.xml
src/zettwerk/mobiletheming/profiles/default/metadata.xml
src/zettwerk/mobiletheming/profiles/default/registry.xml
src/zettwerk/mobiletheming/tests/__init__.py
src/zettwerk/mobiletheming/tests/robot_test.txt
src/zettwerk/mobiletheming/tests/test_example.py
src/zettwerk/mobiletheming/tests/test_robot.py