Metadata-Version: 1.1
Name: zettwerk.mobiletheming
Version: 0.2
Summary: Switching mobile themes based on urls in plone.
Home-page: http://www.zettwerk.com
Author: Jörg Kubaile / zettwerk GmbH
Author-email: jk@zettwerk.com
License: gpl
Keywords: mobile
Platform: UNKNOWN
Classifier: Environment :: Web Environment
Classifier: Framework :: Plone
Classifier: Operating System :: OS Independent
Classifier: Programming Language :: Python
Classifier: Programming Language :: Python :: 2.6
Classifier: Topic :: Software Development :: Libraries :: Python Modules
